<annotation>
	<folder>Varada_s Raw Images</folder>
	<filename>LABEL_20210614_1303_1_1849.png</filename>
	<path>C:\Users\varad\Desktop\PhucLabs\Vision\Varada_s Raw Images-20210701T035001Z-001\Varada_s Raw Images\LABEL_20210614_1303_1_1849.png</path>
	<source>
		<database>Unknown</database>
	</source>
	<size>
		<width>420</width>
		<height>70</height>
		<depth>3</depth>
	</size>
	<segmented>0</segmented>
	<object>
		<name>bubble</name>
		<pose>Unspecified</pose>
		<truncated>0</truncated>
		<difficult>0</difficult>
		<bndbox>
			<xmin>294</xmin>
			<ymin>18</ymin>
			<xmax>314</xmax>
			<ymax>42</ymax>
		</bndbox>
	</object>
	<object>
		<name>tss</name>
		<pose>Unspecified</pose>
		<truncated>0</truncated>
		<difficult>0</difficult>
		<bndbox>
			<xmin>172</xmin>
			<ymin>16</ymin>
			<xmax>178</xmax>
			<ymax>22</ymax>
		</bndbox>
	</object>
	<object>
		<name>tss</name>
		<pose>Unspecified</pose>
		<truncated>0</truncated>
		<difficult>0</difficult>
		<bndbox>
			<xmin>234</xmin>
			<ymin>41</ymin>
			<xmax>240</xmax>
			<ymax>47</ymax>
		</bndbox>
	</object>
	<object>
		<name>tss</name>
		<pose>Unspecified</pose>
		<truncated>0</truncated>
		<difficult>0</difficult>
		<bndbox>
			<xmin>130</xmin>
			<ymin>61</ymin>
			<xmax>135</xmax>
			<ymax>67</ymax>
		</bndbox>
	</object>
	<object>
		<name>tss</name>
		<pose>Unspecified</pose>
		<truncated>0</truncated>
		<difficult>0</difficult>
		<bndbox>
			<xmin>409</xmin>
			<ymin>40</ymin>
			<xmax>414</xmax>
			<ymax>46</ymax>
		</bndbox>
	</object>
	<object>
		<name>tss</name>
		<pose>Unspecified</pose>
		<truncated>0</truncated>
		<difficult>0</difficult>
		<bndbox>
			<xmin>26</xmin>
			<ymin>39</ymin>
			<xmax>31</xmax>
			<ymax>45</ymax>
		</bndbox>
	</object>
	<object>
		<name>tss</name>
		<pose>Unspecified</pose>
		<truncated>0</truncated>
		<difficult>0</difficult>
		<bndbox>
			<xmin>414</xmin>
			<ymin>24</ymin>
			<xmax>419</xmax>
			<ymax>31</ymax>
		</bndbox>
	</object>
</annotation>
