<annotation>
	<folder>Varada_s Raw Images</folder>
	<filename>LABEL_20210614_1303_1_2198.png</filename>
	<path>C:\Users\varad\Desktop\PhucLabs\Vision\Varada_s Raw Images-20210701T035001Z-001\Varada_s Raw Images\LABEL_20210614_1303_1_2198.png</path>
	<source>
		<database>Unknown</database>
	</source>
	<size>
		<width>420</width>
		<height>70</height>
		<depth>3</depth>
	</size>
	<segmented>0</segmented>
	<object>
		<name>bubble</name>
		<pose>Unspecified</pose>
		<truncated>0</truncated>
		<difficult>0</difficult>
		<bndbox>
			<xmin>2</xmin>
			<ymin>28</ymin>
			<xmax>11</xmax>
			<ymax>41</ymax>
		</bndbox>
	</object>
	<object>
		<name>tss</name>
		<pose>Unspecified</pose>
		<truncated>0</truncated>
		<difficult>0</difficult>
		<bndbox>
			<xmin>206</xmin>
			<ymin>27</ymin>
			<xmax>212</xmax>
			<ymax>32</ymax>
		</bndbox>
	</object>
	<object>
		<name>tss</name>
		<pose>Unspecified</pose>
		<truncated>0</truncated>
		<difficult>0</difficult>
		<bndbox>
			<xmin>330</xmin>
			<ymin>41</ymin>
			<xmax>336</xmax>
			<ymax>48</ymax>
		</bndbox>
	</object>
	<object>
		<name>bubble</name>
		<pose>Unspecified</pose>
		<truncated>0</truncated>
		<difficult>0</difficult>
		<bndbox>
			<xmin>341</xmin>
			<ymin>14</ymin>
			<xmax>347</xmax>
			<ymax>23</ymax>
		</bndbox>
	</object>
	<object>
		<name>tss</name>
		<pose>Unspecified</pose>
		<truncated>0</truncated>
		<difficult>0</difficult>
		<bndbox>
			<xmin>27</xmin>
			<ymin>39</ymin>
			<xmax>32</xmax>
			<ymax>44</ymax>
		</bndbox>
	</object>
	<object>
		<name>tss</name>
		<pose>Unspecified</pose>
		<truncated>0</truncated>
		<difficult>0</difficult>
		<bndbox>
			<xmin>370</xmin>
			<ymin>63</ymin>
			<xmax>375</xmax>
			<ymax>67</ymax>
		</bndbox>
	</object>
</annotation>
